{
  "new_game_spawner": {
    "object_type": "node",
    "position": [
      8,
      9
    ]
  },
  "cutscene_imedes_renald": {
    "object_type": "imedes_renald",
    "args": {
      "spritesheet": [
        "Imedes Renald Chokehold",
        0,
        0
      ]
    },
    "position": [
      6,
      1
    ]
  },
  "head_wizard": {
    "object_type": "npc",
    "args": {
      "spritesheet": [
        "Generic People",
        0,
        6
      ]
    },
    "position": [
      8,
      4
    ]
  },
  "student_3": {
    "object_type": "npcstudent",
    "skin_color": 5,
    "args": {
      "name": "Mei-Hua",
      "dialog_key": "student_3#after_fight"
    },
    "position": [
      7,
      9
    ]
  }
}